sphinx_mcp/__init__.py
sphinx_mcp/common.py
sphinx_mcp/mcpdocs.py
sphinx_mcp/utils.py
sphinx_mcp-0.1.2.dist-info/METADATA
sphinx_mcp-0.1.2.dist-info/WHEEL
sphinx_mcp-0.1.2.dist-info/entry_points.txt
sphinx_mcp-0.1.2.dist-info/licenses/LICENSE
sphinx_mcp-0.1.2.dist-info/RECORD
