Metadata-Version: 2.4
Name: sphinx-mcp
Version: 0.1.2
Summary: Sphinx extension for documenting MCP tools, prompts, resources and resource templates.
Author-email: Anirban Basu <anirbanbasu@users.noreply.github.com>
License-File: LICENSE
Keywords: documentation,mcp,model-context-protocol,python3,sphinx,sphinx-doc,sphinx-documentation,sphinx-extension
Classifier: Development Status :: 3 - Alpha
Classifier: Framework :: Sphinx
Classifier: Framework :: Sphinx :: Extension
Classifier: Intended Audience :: Developers
Classifier: License :: OSI Approved :: BSD License
Classifier: Programming Language :: Python :: 3.12
Classifier: Topic :: Documentation
Classifier: Topic :: Documentation :: Sphinx
Requires-Python: >=3.12
Requires-Dist: fastmcp>=2.4.0
Requires-Dist: pymcp-template>=0.1.2
Requires-Dist: python-dotenv>=1.1.1
